Metadata-Version: 2.4
Name: geosmith
Version: 0.1.0
Summary: *Smith for ML models
Author-email: "Kyle T. Jones" <kyletjones@gmail.com>
Maintainer-email: "Kyle T. Jones" <kyletjones@gmail.com>
License-Expression: MIT
Project-URL: Homepage, https://github.com/kylejones200/geosmith
Project-URL: Documentation, https://geosmith.readthedocs.io/
Project-URL: Repository, https://github.com/kylejones200/geosmith
Project-URL: Bug Tracker, https://github.com/kylejones200/geosmith/issues
Project-URL: Changelog, https://github.com/kylejones200/geosmith/blob/main/CHANGELOG.md
Requires-Python: >=3.12
License-File: LICENSE
Requires-Dist: numpy>=1.24.0
Requires-Dist: pandas>=2.0.0
Requires-Dist: timesmith>=0.1.0
Provides-Extra: vector
Requires-Dist: geopandas>=0.14.0; extra == "vector"
Requires-Dist: shapely>=2.0.0; extra == "vector"
Requires-Dist: pyproj>=3.6.0; extra == "vector"
Provides-Extra: raster
Requires-Dist: rasterio>=1.3.0; extra == "raster"
Requires-Dist: xarray>=2023.0.0; extra == "raster"
Provides-Extra: viz
Requires-Dist: matplotlib>=3.7.0; extra == "viz"
Provides-Extra: timesmith
Requires-Dist: timesmith>=0.1.0; extra == "timesmith"
Provides-Extra: plotsmith
Requires-Dist: plotsmith>=0.1.0; extra == "plotsmith"
Provides-Extra: anomsmith
Requires-Dist: anomsmith>=0.1.0; extra == "anomsmith"
Provides-Extra: ml
Requires-Dist: scikit-learn>=1.3.0; extra == "ml"
Provides-Extra: seismic
Requires-Dist: segyio>=1.9.0; extra == "seismic"
Provides-Extra: dev
Requires-Dist: pytest>=7.0; extra == "dev"
Requires-Dist: pytest-cov>=4.0; extra == "dev"
Requires-Dist: black>=23.0; extra == "dev"
Requires-Dist: ruff>=0.1.0; extra == "dev"
Requires-Dist: mypy>=1.5.0; extra == "dev"
Provides-Extra: docs
Requires-Dist: sphinx>=7.0; extra == "docs"
Requires-Dist: sphinx-rtd-theme>=2.0; extra == "docs"
Requires-Dist: sphinx-autodoc-typehints>=1.20; extra == "docs"
Provides-Extra: examples
Requires-Dist: jupyter>=1.0; extra == "examples"
Requires-Dist: notebook>=7.0; extra == "examples"
Requires-Dist: ipykernel>=6.0; extra == "examples"
Provides-Extra: all
Requires-Dist: geosmith[dev,docs,examples,ml,primitives,raster,seismic,vector,viz]; extra == "all"
Dynamic: license-file
